pytest_th/__init__.py
pytest_multithreading-1.0.2.dist-info/METADATA
pytest_multithreading-1.0.2.dist-info/WHEEL
pytest_multithreading-1.0.2.dist-info/entry_points.txt
pytest_multithreading-1.0.2.dist-info/top_level.txt
pytest_multithreading-1.0.2.dist-info/RECORD
