Metadata-Version: 2.1
Name: pytest-multithreading
Version: 1.0.2
Summary: a pytest plugin for th and concurrent testing
Home-page: https://github.com/zhujiahuan/pytest-multithreading
Author: zhujiahuan
Author-email: zhujiahuan@yfcloud.com
License: MIT
Platform: UNKNOWN
Requires-Dist: pytest (>=3.6)
